pyfreeradius/__init__.py
pyfreeradius/helpers.py
pyfreeradius/models.py
pyfreeradius/params.py
pyfreeradius/py.typed
pyfreeradius/repositories.py
pyfreeradius/services.py
pyfreeradius/settings.py
pyfreeradius-1.4.0.dist-info/METADATA
pyfreeradius-1.4.0.dist-info/WHEEL
pyfreeradius-1.4.0.dist-info/licenses/LICENSE
pyfreeradius-1.4.0.dist-info/RECORD
