Metadata-Version: 2.4
Name: pyfreeradius
Version: 1.4.0
Summary: A Python API on top of the FreeRADIUS database schema
Project-URL: Homepage, https://github.com/angely-dev/pyfreeradius
Project-URL: Bug Tracker, https://github.com/angely-dev/pyfreeradius/issues
Author-email: angely-dev <contact@brindereseau.fr>
License-File: LICENSE
Classifier: License :: OSI Approved :: MIT License
Classifier: Programming Language :: Python :: 3
Classifier: Programming Language :: Python :: 3.10
Classifier: Programming Language :: Python :: 3.11
Classifier: Programming Language :: Python :: 3.12
Classifier: Programming Language :: Python :: 3.13
Classifier: Topic :: System :: Networking
Requires-Python: >=3.10
Requires-Dist: pydantic
